MANIFEST.in
README.rst
buildout.cfg
develop.cfg
requirements.txt
setup.py
version.txt
bob/__init__.py
bob.db.youtube.egg-info/PKG-INFO
bob.db.youtube.egg-info/SOURCES.txt
bob.db.youtube.egg-info/dependency_links.txt
bob.db.youtube.egg-info/entry_points.txt
bob.db.youtube.egg-info/not-zip-safe
bob.db.youtube.egg-info/requires.txt
bob.db.youtube.egg-info/top_level.txt
bob/db/__init__.py
bob/db/youtube/__init__.py
bob/db/youtube/create.py
bob/db/youtube/driver.py
bob/db/youtube/models.py
bob/db/youtube/query.py
bob/db/youtube/test.py
bob/db/youtube/protocol/Youtube_labels.mat
bob/db/youtube/protocol/Youtube_names.txt
bob/db/youtube/protocol/Youtube_splits.mat
doc/conf.py
doc/guide.rst
doc/index.rst
doc/py_api.rst